str_joiner/__init__.py
str_joiner/version.py
str_joiner-0.0.3.dist-info/LICENSE
str_joiner-0.0.3.dist-info/METADATA
str_joiner-0.0.3.dist-info/WHEEL
str_joiner-0.0.3.dist-info/top_level.txt
str_joiner-0.0.3.dist-info/RECORD
