Metadata-Version: 2.2
Name: str_joiner
Version: 0.0.3
Summary: String joiner library
Author-email: NTPro <info@ntprog.com>
License: Copyright (c) 2025 NT Progress LLC
Project-URL: repository, https://gitverse.ru/dmitry-vetrov/str_joiner
Project-URL: homepage, https://gitverse.ru/dmitry-vetrov/str_joiner
Classifier: Programming Language :: Python :: 3
Classifier: License :: OSI Approved :: MIT License
Classifier: Operating System :: OS Independent
Requires-Python: >=3.10
License-File: LICENSE
Provides-Extra: dev
Requires-Dist: build; extra == "dev"
Requires-Dist: nox; extra == "dev"
Requires-Dist: pytest; extra == "dev"
Requires-Dist: pylint; extra == "dev"
Requires-Dist: twine; extra == "dev"
